dj_static_revision/__init__.py
dj_static_revision/context_processors.py
dj_static_revision/py.typed
dj_static_revision/utils.py
dj_static_revision-0.10.dist-info/WHEEL
dj_static_revision-0.10.dist-info/METADATA
dj_static_revision-0.10.dist-info/RECORD
