Metadata-Version: 2.4
Name: dj-static-revision
Version: 0.10
Summary: Revision info for Django static file
Keywords: django,static,version,cache
Author-email: Nguyễn Hồng Quân <ng.hong.quan@gmail.com>
Requires-Python: <4.0,>=3.10
Classifier: Framework :: Django
Classifier: Framework :: Django :: 4.0
Classifier: Framework :: Django :: 4.1
Classifier: Framework :: Django :: 4.2
Classifier: Framework :: Django :: 5.0
Classifier: Framework :: Django :: 5.1
Classifier: Framework :: Django :: 5.2
Classifier: Environment :: Web Environment
Classifier: Topic :: Software Development :: Libraries :: Python Modules
Requires-Dist: dulwich >= 0.24
Project-URL: homepage, https://github.com/AgriConnect/dj-static-revision
Project-URL: repository, https://github.com/AgriConnect/dj-static-revision.git
